pagesage/__init__.py
pagesage/__main__.py
pagesage/auth.py
pagesage/template.py
pagesage-0.0.6.dist-info/METADATA
pagesage-0.0.6.dist-info/WHEEL
pagesage-0.0.6.dist-info/entry_points.txt
pagesage-0.0.6.dist-info/top_level.txt
pagesage-0.0.6.dist-info/RECORD
