Metadata-Version: 2.4
Name: pagesage
Version: 0.0.6
Summary: pagesage - Serve markdown pages and files as static website.
Home-page: https://gitlab.com/nul.one/pagesage
Download-URL: https://gitlab.com/nul.one/pagesage/-/archive/0.0.6/pagesage-0.0.6.tar.gz
Author: Predrag Mandic
Author-email: predrag@nul.one
License: BSD
Classifier: Development Status :: 3 - Alpha
Classifier: Environment :: Console
Classifier: Intended Audience :: Information Technology
Classifier: License :: OSI Approved :: BSD License
Classifier: Natural Language :: English
Classifier: Operating System :: POSIX :: Linux
Classifier: Programming Language :: Python :: 3 :: Only
Requires-Python: >=3.11.2
Requires-Dist: Flask<4,>=3.0.3
Requires-Dist: Markdown<4,>=3.6
Requires-Dist: click<9,>=8.1.7
Requires-Dist: pygments<3,>=2.18.0
Dynamic: author
Dynamic: author-email
Dynamic: classifier
Dynamic: description
Dynamic: description-content-type
Dynamic: download-url
Dynamic: home-page
Dynamic: license
Dynamic: requires-dist
Dynamic: requires-python
Dynamic: summary
